pycosh/CoshConfig.py
pycosh/CoshXcorr.py
pycosh/__init__.py
pycosh-0.0.0.dist-info/METADATA
pycosh-0.0.0.dist-info/WHEEL
pycosh-0.0.0.dist-info/top_level.txt
pycosh-0.0.0.dist-info/RECORD
