Metadata-Version: 2.1
Name: pycosh
Version: 0.0.0
Summary: correlated self-heterodyne (COSH) optical noise analyzer
Home-page: https://github.com/MaodongGao/pycosh
Author: Zhiquan Yuan, Heming Wang, Peng Liu, Bohan Li, Boqiang Shen, Maodong Gao
Author-email: mgao@caltech.edu
License: UNKNOWN
Platform: UNKNOWN
Requires-Dist: numpy
Requires-Dist: scipy
Requires-Dist: matplotlib
